semantic_link_labs-0.12.10.dist-info/licenses/LICENSE
sempy_labs/__init__.py
sempy_labs/_a_lib_info.py
sempy_labs/_ai.py
sempy_labs/_authentication.py
sempy_labs/_capacities.py
sempy_labs/_capacity_migration.py
sempy_labs/_catalog.py
sempy_labs/_clear_cache.py
sempy_labs/_connections.py
sempy_labs/_dashboards.py
sempy_labs/_data_access_security.py
sempy_labs/_data_pipelines.py
sempy_labs/_dataflows.py
sempy_labs/_dax.py
sempy_labs/_daxformatter.py
sempy_labs/_delta_analyzer.py
sempy_labs/_delta_analyzer_history.py
sempy_labs/_dictionary_diffs.py
sempy_labs/_documentation.py
sempy_labs/_domains.py
sempy_labs/_eventhouses.py
sempy_labs/_external_data_shares.py
sempy_labs/_gateways.py
sempy_labs/_generate_semantic_model.py
sempy_labs/_get_connection_string.py
sempy_labs/_git.py
sempy_labs/_graphQL.py
sempy_labs/_helper_functions.py
sempy_labs/_icons.py
sempy_labs/_job_scheduler.py
sempy_labs/_kql_databases.py
sempy_labs/_kql_querysets.py
sempy_labs/_kusto.py
sempy_labs/_labels.py
sempy_labs/_list_functions.py
sempy_labs/_managed_private_endpoints.py
sempy_labs/_mirrored_databases.py
sempy_labs/_mirrored_warehouses.py
sempy_labs/_ml_experiments.py
sempy_labs/_model_auto_build.py
sempy_labs/_model_bpa.py
sempy_labs/_model_bpa_bulk.py
sempy_labs/_model_bpa_rules.py
sempy_labs/_model_dependencies.py
sempy_labs/_mounted_data_factories.py
sempy_labs/_notebooks.py
sempy_labs/_one_lake_integration.py
sempy_labs/_onelake.py
sempy_labs/_query_scale_out.py
sempy_labs/_refresh_semantic_model.py
sempy_labs/_semantic_models.py
sempy_labs/_spark.py
sempy_labs/_sql.py
sempy_labs/_sql_audit_settings.py
sempy_labs/_sql_endpoints.py
sempy_labs/_tags.py
sempy_labs/_takeover.py
sempy_labs/_translations.py
sempy_labs/_user_delegation_key.py
sempy_labs/_utils.py
sempy_labs/_vertipaq.py
sempy_labs/_vpax.py
sempy_labs/_warehouses.py
sempy_labs/_workloads.py
sempy_labs/_workspace_identity.py
sempy_labs/_workspaces.py
sempy_labs/_bpa_translation/_model/_translations_am-ET.po
sempy_labs/_bpa_translation/_model/_translations_ar-AE.po
semantic_link_labs-0.12.10.dist-info/METADATA
semantic_link_labs-0.12.10.dist-info/WHEEL
semantic_link_labs-0.12.10.dist-info/top_level.txt
semantic_link_labs-0.12.10.dist-info/RECORD
