Metadata-Version: 2.4
Name: semantic-link-labs
Version: 0.12.10
Summary: Semantic Link Labs for Microsoft Fabric
Author: Microsoft Corporation
License: MIT License
Project-URL: Repository, https://github.com/microsoft/semantic-link-labs.git
Classifier: Development Status :: 3 - Alpha
Classifier: Intended Audience :: Developers
Classifier: Intended Audience :: Education
Classifier: Intended Audience :: Science/Research
Classifier: Programming Language :: Python :: 3.10
Classifier: Programming Language :: Python :: 3 :: Only
Classifier: Framework :: Jupyter
Requires-Python: <3.12,>=3.10
License-File: LICENSE
Requires-Dist: semantic-link-sempy>=0.13.0
Requires-Dist: anytree
Requires-Dist: polib
Requires-Dist: jsonpath_ng
Provides-Extra: test
Requires-Dist: pytest>=8.2.1; extra == "test"
Dynamic: license-file
